MANIFEST.in
README.md
setup.py
hyperterm/__init__.py
hyperterm_utils.egg-info/PKG-INFO
hyperterm_utils.egg-info/SOURCES.txt
hyperterm_utils.egg-info/dependency_links.txt
hyperterm_utils.egg-info/top_level.txt