Metadata-Version: 1.0
Name: hyperterm-utils
Version: 0.1.0
Summary: Python build tools and utilities for Hyperterm
Home-page: https://github.com/mikeanthonywild/hyperterm-utils
Author: Mike Wild
Author-email: mike@mikeanthonywild.com
License: MIT
Platform: UNKNOWN
